ivybloom_cli/__init__.py
ivybloom_cli/main.py
ivybloom_cli/client/__init__.py
ivybloom_cli/client/account.py
ivybloom_cli/client/api_client.py
ivybloom_cli/client/base.py
ivybloom_cli/client/config_client.py
ivybloom_cli/client/data_files.py
ivybloom_cli/client/exports.py
ivybloom_cli/client/jobs.py
ivybloom_cli/client/projects.py
ivybloom_cli/client/reports.py
ivybloom_cli/client/tools.py
ivybloom_cli/client/workflows.py
ivybloom_cli/commands/__init__.py
ivybloom_cli/commands/account.py
ivybloom_cli/commands/auth.py
ivybloom_cli/commands/batch.py
ivybloom_cli/commands/config.py
ivybloom_cli/commands/data.py
ivybloom_cli/commands/exports.py
ivybloom_cli/commands/jobs.py
ivybloom_cli/commands/projects.py
ivybloom_cli/commands/reports.py
ivybloom_cli/commands/run.py
ivybloom_cli/commands/tools.py
ivybloom_cli/commands/workflows.py
ivybloom_cli/commands/run_helpers/__init__.py
ivybloom_cli/commands/run_helpers/params.py
ivybloom_cli/commands/run_helpers/schema.py
ivybloom_cli/tui/__init__.py
ivybloom_cli/tui/accel.py
ivybloom_cli/tui/accelerated_text.py
ivybloom_cli/tui/app.py
ivybloom_cli/tui/artifact_preview.py
ivybloom_cli/tui/artifact_visualizer.py
ivybloom_cli/tui/artifacts_service.py
ivybloom_cli/tui/cli_helpers.py
ivybloom_cli/tui/cli_runner.py
ivybloom_cli/tui/commands_controller.py
ivybloom_cli/tui/debug_logger.py
ivybloom_cli/tui/details_controller.py
ivybloom_cli/tui/history.py
ivybloom_cli/tui/jobs_service.py
ivybloom_cli/tui/panels.py
ivybloom_cli/tui/project_controller.py
ivybloom_cli/tui/projects_service.py
ivybloom_cli/tui/protein_visualizer.py
ivybloom_cli/tui/responsive.py
ivybloom_cli/tui/screens.py
ivybloom_cli/tui/search.py
ivybloom_cli/tui/smiles_visualizer.py
ivybloom_cli/tui/status.py
ivybloom_cli/tui/streaming.py
ivybloom_cli/tui/structure_service.py
ivybloom_cli/tui/textual_shim.py
ivybloom_cli/tui/theme.py
ivybloom_cli/tui/types.py
ivybloom_cli/tui/views.py
ivybloom_cli/tui/commands/__init__.py
ivybloom_cli/tui/commands/account_cmds.py
ivybloom-0.8.0.dist-info/METADATA
ivybloom-0.8.0.dist-info/WHEEL
ivybloom-0.8.0.dist-info/entry_points.txt
ivybloom-0.8.0.dist-info/top_level.txt
ivybloom-0.8.0.dist-info/RECORD
