Metadata-Version: 2.4
Name: ivybloom
Version: 0.8.0
Summary: Command-line interface for computational biology and drug discovery
Author-email: Ivy Biosciences <support@ivybiosciences.com>
Maintainer-email: Ivy Biosciences <support@ivybiosciences.com>
License: MIT
Project-URL: Homepage, https://ivybiosciences.com
Project-URL: Documentation, https://docs.ivybiosciences.com/cli
Project-URL: Repository, https://github.com/ivybiosciences/ivybloom-cli
Project-URL: Bug Tracker, https://github.com/ivybiosciences/ivybloom-cli/issues
Project-URL: Changelog, https://github.com/ivybiosciences/ivybloom-cli/blob/main/CHANGELOG.md
Project-URL: Source Code, https://github.com/ivybiosciences/ivybloom-cli
Keywords: bioinformatics,computational biology,drug discovery,molecular modeling,cli,api
Classifier: Development Status :: 4 - Beta
Classifier: Intended Audience :: Science/Research
Classifier: Intended Audience :: Developers
Classifier: License :: OSI Approved :: MIT License
Classifier: Operating System :: OS Independent
Classifier: Programming Language :: Python :: 3
Classifier: Programming Language :: Python :: 3.8
Classifier: Programming Language :: Python :: 3.9
Classifier: Programming Language :: Python :: 3.10
Classifier: Programming Language :: Python :: 3.11
Classifier: Programming Language :: Python :: 3.12
Classifier: Topic :: Scientific/Engineering :: Bio-Informatics
Classifier: Topic :: Scientific/Engineering :: Chemistry
Classifier: Topic :: Software Development :: Libraries :: Python Modules
Classifier: Environment :: Console
Classifier: Operating System :: MacOS
Classifier: Operating System :: Microsoft :: Windows
Classifier: Operating System :: POSIX :: Linux
Requires-Python: >=3.8
Requires-Dist: click>=8.0.0
Requires-Dist: rich>=13.0.0
Requires-Dist: httpx>=0.24.0
Requires-Dist: keyring>=23.0.0
Requires-Dist: appdirs>=1.4.0
Requires-Dist: pydantic>=2.0.0
Requires-Dist: pyyaml>=6.0.0
Requires-Dist: requests>=2.28.0
Requires-Dist: numpy>=1.22
Requires-Dist: jsonschema>=4.20.0
Requires-Dist: InquirerPy>=0.3.4
Requires-Dist: prompt_toolkit>=3.0.36
Requires-Dist: click-didyoumean>=0.3.0
Requires-Dist: click-completion>=0.5.2
Requires-Dist: click-repl>=0.3.0
Requires-Dist: rich-click>=1.7.3
Requires-Dist: humanize>=4.9.0
Requires-Dist: textual<0.60,>=0.55
Requires-Dist: asciimol>=1.2.0
Requires-Dist: ase>=3.22.0
Requires-Dist: flatprot
Requires-Dist: cryptography>=41.0.0
Provides-Extra: dev
Requires-Dist: pytest>=7.0.0; extra == "dev"
Requires-Dist: pytest-cov>=4.0.0; extra == "dev"
Requires-Dist: pytest-asyncio>=0.21.0; extra == "dev"
Requires-Dist: pytest-mock>=3.10.0; extra == "dev"
Requires-Dist: black>=23.0.0; extra == "dev"
Requires-Dist: flake8>=6.0.0; extra == "dev"
Requires-Dist: mypy>=1.0.0; extra == "dev"
Requires-Dist: pre-commit>=3.0.0; extra == "dev"
Requires-Dist: types-PyYAML>=6.0.0; extra == "dev"
Requires-Dist: types-requests>=2.28.0; extra == "dev"
Provides-Extra: docs
Requires-Dist: mkdocs>=1.4.0; extra == "docs"
Requires-Dist: mkdocs-material>=9.0.0; extra == "docs"
Requires-Dist: mkdocs-click>=0.8.0; extra == "docs"
Requires-Dist: mkdocs-mermaid2-plugin>=0.6.0; extra == "docs"
Provides-Extra: test
Requires-Dist: pytest>=7.0.0; extra == "test"
Requires-Dist: pytest-cov>=4.0.0; extra == "test"
Requires-Dist: pytest-asyncio>=0.21.0; extra == "test"
Requires-Dist: pytest-mock>=3.10.0; extra == "test"
Requires-Dist: coverage>=7.0.0; extra == "test"
